{
  "dankActions": {
    "enabled": false
  },
  "easyEffects": {
    "enabled": true,
    "currentOutputIndex": -1,
    "currentInputIndex": -1
  },
  "grimblast": {
    "enabled": false
  },
  "powerUsagePlugin": {
    "enabled": true
  },
  "wallpaperBing": {
    "enabled": true
  },
  "wallpaperDiscovery": {
    "enabled": true,
    "lastWallpaperUsed": "wallhaven.cc"
  },
  "worldClock": {
    "enabled": true,
    "timezones": []
  },
  "razer": {
    "enabled": true
  },
  "dankGifSearch": {
    "enabled": true,
    "trigger": ":g",
    "preferredFormat": "webp",
    "pasteUrlOnly": false
  },
  "dankKDEConnect": {
    "enabled": false
  },
  "emojiLauncher": {
    "enabled": true
  }
}